LICENSE
clouddrive_proxy/.DS_Store
clouddrive_proxy/__init__.py
clouddrive_proxy/__main__.py
clouddrive_proxy/py.typed
python_clouddrive_proxy-0.0.1.dist-info/LICENSE
python_clouddrive_proxy-0.0.1.dist-info/METADATA
python_clouddrive_proxy-0.0.1.dist-info/WHEEL
python_clouddrive_proxy-0.0.1.dist-info/entry_points.txt
python_clouddrive_proxy-0.0.1.dist-info/RECORD
