Metadata-Version: 2.1
Name: python-clouddrive-proxy
Version: 0.0.1
Summary: Python clouddrive reverse proxy.
Home-page: https://github.com/ChenyangGao/web-mount-packs/tree/main/python-clouddrive-proxy
License: MIT
Keywords: clouddrive,reverse proxy
Author: ChenyangGao
Author-email: wosiwujm@gmail.com
Requires-Python: >=3.12,<4.0
Classifier: Development Status :: 4 - Beta
Classifier: Intended Audience :: Developers
Classifier: License :: OSI Approved :: MIT License
Classifier: Operating System :: OS Independent
Classifier: Programming Language :: Python
Classifier: Programming Language :: Python :: 3
Classifier: Programming Language :: Python :: 3.12
Classifier: Programming Language :: Python :: 3.13
Classifier: Programming Language :: Python :: 3 :: Only
Classifier: Topic :: Software Development
Classifier: Topic :: Software Development :: Libraries
Classifier: Topic :: Software Development :: Libraries :: Python Modules
Requires-Dist: blacksheep
Requires-Dist: clouddrive (>=0.0.12.7.1)
Requires-Dist: httpx
Requires-Dist: protobuf
Requires-Dist: python-reverse-proxy (>=0.0.9.4)
Requires-Dist: sqlitetools (>=0.0.2.1)
Requires-Dist: uvicorn
Project-URL: Repository, https://github.com/ChenyangGao/web-mount-packs/tree/main/python-clouddrive-proxy
